api_data_logger/__init__.py
api_data_logger/utils.py
api_logger-0.1.0.dist-info/METADATA
api_logger-0.1.0.dist-info/WHEEL
api_logger-0.1.0.dist-info/top_level.txt
api_logger-0.1.0.dist-info/RECORD
