Metadata-Version: 2.4
Name: api-logger
Version: 0.1.0
Summary: Logs API requests and responses and uploads them to S3
Author-email: Your Name <you@example.com>
Requires-Dist: aioboto3
Requires-Dist: fastapi
